lspace/__init__.py
lspace/api_v1_blueprint/__init__.py
lspace/api_v1_blueprint/resource_helpers.py
lspace/api_v1_blueprint/models/__init__.py
lspace/api_v1_blueprint/resources/__init__.py
lspace/api_v1_blueprint/resources/book.py
lspace/api_v1_blueprint/resources/book_file.py
lspace/api_v1_blueprint/resources/version.py
lspace/cli/__init__.py
lspace/cli/db_command.py
lspace/cli/export_command.py
lspace/cli/init_command.py
lspace/cli/list_command.py
lspace/cli/reimport_command.py
lspace/cli/remove_command.py
lspace/cli/version_command.py
lspace/cli/web_command.py
lspace/cli/import_command/__init__.py
lspace/cli/import_command/_import.py
lspace/cli/import_command/add_book_to_db.py
lspace/cli/import_command/add_to_shelf.py
lspace/cli/import_command/base_helper.py
lspace/cli/import_command/check_if_in_library.py
lspace/cli/import_command/copy_to_library.py
lspace/cli/import_command/import_from_calibre.py
lspace/cli/import_command/add_to_shelf_options/__init__.py
lspace/cli/import_command/add_to_shelf_options/_options.py
lspace/cli/import_command/add_to_shelf_options/put_in_default_shelf.py
lspace/cli/import_command/add_to_shelf_options/put_in_new_shelf.py
lspace/cli/import_command/import_from_api/__init__.py
lspace/cli/import_command/import_options/__init__.py
lspace/cli/import_command/import_options/_options.py
lspace/cli/import_command/import_options/isbn_lookup.py
lspace/cli/import_command/import_options/manual_import.py
lspace/cli/import_command/import_options/manual_search.py
lspace/cli/import_command/import_options/peek.py
lspace/cli/import_command/import_options/skip_book.py
lspace/cli/tools_command/__init__.py
lspace/cli/tools_command/clear_cache.py
lspace/cli/tools_command/rebuild_search_index.py
lspace/cli/tools_command/update_paths.py
lspace/file_types/__init__.py
lspace/file_types/_base.py
lspace/file_types/epub.py
lspace/file_types/pdf.py
lspace/frontend_blueprint/__init__.py
lspace/frontend_blueprint/static/bulma.min.css
lspace-0.4.8.dist-info/LICENSE
lspace-0.4.8.dist-info/METADATA
lspace-0.4.8.dist-info/WHEEL
lspace-0.4.8.dist-info/entry_points.txt
lspace-0.4.8.dist-info/top_level.txt
lspace-0.4.8.dist-info/RECORD
