Metadata-Version: 2.1
Name: lspace
Version: 0.4.8
Summary: ebook manager built around isbnlib
Home-page: https://github.com/puhoy/lspace
Author: jan
Author-email: stuff@kwoh.de
Classifier: Development Status :: 4 - Beta
Classifier: Environment :: Console
Classifier: Intended Audience :: End Users/Desktop
Classifier: Natural Language :: English
Classifier: Topic :: Utilities
Classifier: Programming Language :: Python :: 3.7
Classifier: Programming Language :: Python :: 3.8
Classifier: Programming Language :: Python :: 3.9
Classifier: Programming Language :: Python :: 3.10
License-File: LICENSE
Requires-Dist: alembic ==1.11.1
Requires-Dist: aniso8601 ==9.0.1
Requires-Dist: apispec ==6.3.0
Requires-Dist: attrs ==23.1.0
Requires-Dist: blinker ==1.6.2
Requires-Dist: certifi ==2023.5.7
Requires-Dist: chardet ==5.1.0
Requires-Dist: Click ==8.1.4
Requires-Dist: colorama ==0.4.6
Requires-Dist: EbookLib ==0.18
Requires-Dist: Flask ==2.3.2
Requires-Dist: Flask-Migrate ==4.0.4
Requires-Dist: flask-restx ==1.1.0
Requires-Dist: Flask-SQLAlchemy ==3.0.5
Requires-Dist: flask-whooshee ==0.9.1
Requires-Dist: Flask-WTF ==1.1.1
Requires-Dist: gunicorn ==20.1.0
Requires-Dist: html2text ==2020.1.16
Requires-Dist: idna ==3.4
Requires-Dist: isbnlib ==3.10.14
Requires-Dist: itsdangerous ==2.1.2
Requires-Dist: Jinja2 ==3.1.2
Requires-Dist: jsonschema ==4.18.1
Requires-Dist: lxml ==4.9.3
Requires-Dist: Mako ==1.2.4
Requires-Dist: MarkupSafe ==2.1.3
Requires-Dist: marshmallow ==3.19.0
Requires-Dist: PyPDF2 ==3.0.1
Requires-Dist: pyrsistent ==0.19.3
Requires-Dist: python-dateutil ==2.8.2
Requires-Dist: python-editor ==1.0.4
Requires-Dist: python-slugify ==8.0.1
Requires-Dist: pytz ==2023.3
Requires-Dist: PyYAML ==6.0.1
Requires-Dist: requests ==2.31.0
Requires-Dist: six ==1.16.0
Requires-Dist: SQLAlchemy ==2.0.18
Requires-Dist: text-unidecode ==1.3
Requires-Dist: typing ==3.7.4.3
Requires-Dist: urllib3 ==2.0.3
Requires-Dist: Werkzeug ==2.3.6
Requires-Dist: Whoosh ==2.7.4
Requires-Dist: WTForms ==3.0.1
Provides-Extra: dev
Requires-Dist: pytest ==7.4.0 ; extra == 'dev'
Requires-Dist: pytest-cov ==4.1.0 ; extra == 'dev'
Requires-Dist: pytest-cover ==3.0.0 ; extra == 'dev'
Requires-Dist: codecov ==2.1.13 ; extra == 'dev'
Requires-Dist: ipython ==8.14.0 ; extra == 'dev'
Requires-Dist: doit ==0.36.0 ; extra == 'dev'
Requires-Dist: wheel ==0.40.0 ; extra == 'dev'
Requires-Dist: twine ==5.1.1 ; extra == 'dev'
Requires-Dist: build ==0.10.0 ; extra == 'dev'
Requires-Dist: bump2version ==1.0.1 ; extra == 'dev'
Provides-Extra: test
Requires-Dist: pytest ==7.4.0 ; extra == 'test'
Requires-Dist: pytest-cov ==4.1.0 ; extra == 'test'
Requires-Dist: pytest-cover ==3.0.0 ; extra == 'test'
Requires-Dist: codecov ==2.1.13 ; extra == 'test'
